README
setup.py
python/__init__.py
python/version.py
python_applescript.egg-info/PKG-INFO
python_applescript.egg-info/SOURCES.txt
python_applescript.egg-info/dependency_links.txt
python_applescript.egg-info/top_level.txt
src/python_applescript.c