Metadata-Version: 1.0
Name: python-applescript
Version: 0.1
Summary: python extension for applescript
Home-page: http://github.com/ohe/python-applescript/
Author: Olivier Hervieu
Author-email: olivier.hervieu@gmail.com
License: MIT
Download-URL: http://github.com/downloads/ohe/python-applescript/python-applescript-0.1.tar.gz
Platform: MacOS X
Classifier: Development Status :: 3 - Alpha
Classifier: License :: OSI Approved :: BSD License
Classifier: Operating System :: MacOS :: MacOS X
Classifier: Programming Language :: C
Classifier: Programming Language :: Python
Classifier: Topic :: Utilities
Classifier: Topic :: Software Development :: Libraries
